hsf/__init__.py
hsf/augmentation.py
hsf/engines.py
hsf/factory.py
hsf/fetch_models.py
hsf/multispectrality.py
hsf/roiloc_wrapper.py
hsf/segment.py
hsf/uncertainty.py
hsf/welcome.py
hsf/conf/__init__.py
hsf/conf/config.yaml
hsf/conf/augmentation/default.yaml
hsf/conf/files/default.yaml
hsf/conf/hardware/deepsparse.yaml
hsf/conf/hardware/onnxruntime.yaml
hsf/conf/hydra/help/hsf.yaml
hsf/conf/multispectrality/default.yaml
hsf/conf/roiloc/default_corot2.yaml
hsf/conf/roiloc/default_t2iso.yaml
hsf/conf/segmentation/bagging_accurate.prev.yaml
hsf/conf/segmentation/bagging_accurate.yaml
hsf/conf/segmentation/bagging_fast.prev.yaml
hsf/conf/segmentation/bagging_fast.yaml
hsf/conf/segmentation/bagging_sq.prev.yaml
hsf/conf/segmentation/single_accurate.prev.yaml
hsf/conf/segmentation/single_accurate.yaml
hsf/conf/segmentation/single_fast.prev.yaml
hsf/conf/segmentation/single_fast.yaml
hsf/conf/segmentation/single_sq.prev.yaml
hsf-1.2.3.dist-info/METADATA
hsf-1.2.3.dist-info/WHEEL
hsf-1.2.3.dist-info/entry_points.txt
hsf-1.2.3.dist-info/licenses/LICENSE.md
hsf-1.2.3.dist-info/RECORD
