Metadata-Version: 2.3
Name: hsf
Version: 1.2.3
Summary: A simple yet exhaustive segmentation tool of the Hippocampal Subfields in T1w and T2w MRIs.
Project-URL: homepage, https://hippomnesis.dev
Project-URL: repository, https://github.com/clementpoiret/ROILoc
Author-email: Clément POIRET <poiret.clement@outlook.fr>
License: MIT License
Keywords: brain,deep learning,hippocampus,mri,segmentation
Classifier: Development Status :: 5 - Production/Stable
Classifier: License :: OSI Approved :: MIT License
Classifier: Topic :: Scientific/Engineering :: Bio-Informatics
Classifier: Topic :: Scientific/Engineering :: Image Processing
Requires-Python: >=3.9
Requires-Dist: antspyx~=0.5.0
Requires-Dist: coverage[toml]~=7.6.0
Requires-Dist: hydra-core~=1.3.0
Requires-Dist: pytest~=8.0.0
Requires-Dist: requests>=2.32.3
Requires-Dist: rich>=11.0.0
Requires-Dist: roiloc>=0.4.1
Requires-Dist: torchio~=0.20.0
Requires-Dist: xxhash~=3.2.0
